odoo/addons/stock_move_line_expiration_date_required/README.rst
odoo/addons/stock_move_line_expiration_date_required/__init__.py
odoo/addons/stock_move_line_expiration_date_required/__manifest__.py
odoo/addons/stock_move_line_expiration_date_required/i18n/es.po
odoo/addons/stock_move_line_expiration_date_required/i18n/it.po
odoo/addons/stock_move_line_expiration_date_required/i18n/stock_move_line_expiration_date_required.pot
odoo/addons/stock_move_line_expiration_date_required/migrations/16.0.1.0.2/post-migration.py
odoo/addons/stock_move_line_expiration_date_required/models/__init__.py
odoo/addons/stock_move_line_expiration_date_required/models/stock_move.py
odoo/addons/stock_move_line_expiration_date_required/models/stock_move_line.py
odoo/addons/stock_move_line_expiration_date_required/models/stock_picking.py
odoo/addons/stock_move_line_expiration_date_required/readme/CONTRIBUTORS.rst
odoo/addons/stock_move_line_expiration_date_required/readme/DESCRIPTION.rst
odoo/addons/stock_move_line_expiration_date_required/readme/USAGE.rst
odoo/addons/stock_move_line_expiration_date_required/static/description/icon.png
odoo/addons/stock_move_line_expiration_date_required/static/description/index.html
odoo/addons/stock_move_line_expiration_date_required/tests/__init__.py
odoo/addons/stock_move_line_expiration_date_required/tests/test_expiration_date_required.py
odoo/addons/stock_move_line_expiration_date_required/views/stock_move_line_view.xml
odoo/addons/stock_move_line_expiration_date_required/views/stock_move_view.xml
odoo_addon_stock_move_line_expiration_date_required-16.0.1.0.2.3.dist-info/METADATA
odoo_addon_stock_move_line_expiration_date_required-16.0.1.0.2.3.dist-info/WHEEL
odoo_addon_stock_move_line_expiration_date_required-16.0.1.0.2.3.dist-info/top_level.txt
odoo_addon_stock_move_line_expiration_date_required-16.0.1.0.2.3.dist-info/RECORD
